pycountry_convert/__init__.py
pycountry_convert/convert_continent_code_to_continent_name.py
pycountry_convert/convert_countries.py
pycountry_convert/convert_country_alpha2_to_continent_code.py
pycountry_convert/country_mappings.py
pycountry_convert/country_name_format.py
pycountry_convert/country_wikipedia.py
pycountry_convert-0.7.0.dist-info/DESCRIPTION.rst
pycountry_convert-0.7.0.dist-info/METADATA
pycountry_convert-0.7.0.dist-info/RECORD
pycountry_convert-0.7.0.dist-info/WHEEL
pycountry_convert-0.7.0.dist-info/metadata.json
pycountry_convert-0.7.0.dist-info/top_level.txt
