Metadata-Version: 2.0
Name: pycountry-convert
Version: 0.7.0
Summary: Extension of Python package pycountry providing conversion functions.
Home-page: https://github.com/TuneLab/pycountry-convert
Author: TUNE Inc.
Author-email: jefft@tune.com
License: MIT License
Download-URL: https://github.com/TuneLab/pycountry-convert/archive/v0.7.0.tar.gz
Keywords: pycountry conversion tune
Platform: UNKNOWN
Classifier: Development Status :: 5 - Production/Stable
Classifier: Intended Audience :: Developers
Classifier: Operating System :: OS Independent
Classifier: Natural Language :: English
Classifier: License :: OSI Approved :: MIT License
Classifier: Programming Language :: Python
Classifier: Programming Language :: Python :: 2.7
Classifier: Programming Language :: Python :: 3
Classifier: Programming Language :: Python :: 3.5
Classifier: Programming Language :: Python :: 3.6
Classifier: Programming Language :: Python :: Implementation :: PyPy
Requires-Dist: pprintpp (>=0.3.0)
Requires-Dist: pycountry (>=16.11.27.1)
Requires-Dist: pytest (>=3.4.0)
Requires-Dist: pytest-mock (>=1.6.3)
Requires-Dist: pytest-cov (>=2.5.1)
Requires-Dist: repoze.lru (>=0.7)
Requires-Dist: wheel (>=0.30.0)
